pyxtend/__init__.py
pyxtend/struct.py
pyxtend/vprint.py
pyxtend-0.4.0.dist-info/LICENSE
pyxtend-0.4.0.dist-info/METADATA
pyxtend-0.4.0.dist-info/WHEEL
pyxtend-0.4.0.dist-info/top_level.txt
pyxtend-0.4.0.dist-info/RECORD
