Metadata-Version: 2.1
Name: pyxtend
Version: 0.4.0
Summary: Some functions for Python
Home-page: https://github.com/jss367/pyxtend
Author: Julius
Author-email: julius.simonelli@gmail.com
Project-URL: Bug Tracker, https://github.com/jss367/pyxtend/issues
Classifier: Programming Language :: Python :: 3
Classifier: License :: OSI Approved :: MIT License
Classifier: Operating System :: OS Independent
Requires-Python: >=3.8
License-File: LICENSE
